equationsdk/__init__.py
equationsdk/device.py
equationsdk/dto.py
equationsdk/equation_api.py
equationsdk/model.py
equationsdk/settings.py
equationsdk/utils.py
equation_sdk-1.0.7.dist-info/LICENSE
equation_sdk-1.0.7.dist-info/METADATA
equation_sdk-1.0.7.dist-info/WHEEL
equation_sdk-1.0.7.dist-info/top_level.txt
equation_sdk-1.0.7.dist-info/RECORD
