Metadata-Version: 2.1
Name: equation-sdk
Version: 1.0.7
Summary: Python SDK for equationconnect.com
Home-page: https://github.com/Ieshaj/equation-sdk
Author: Ieshaj
License: MIT
License-File: LICENSE
Requires-Dist: requests >=2.27.1
Requires-Dist: packaging >=21.2
